{
  "coluna_usuario": "usuario",
  "tabela_que_contem_usuario": "Usuarios",
  "coluna_plano": "plano",
  "tabela_que_contem_plano": "Planos",
  "coluna_historico_de_reproducoes": "historico_id",
  "tabela_que_contem_historico_de_reproducoes": "Historico",
  "coluna_seguindo_artistas": "nome-da-coluna",
  "tabela_que_contem_seguindo_artistas": "Seguindo",
  "coluna_artista": "nome_artista",
  "tabela_que_contem_artista": "Artistas",
  "coluna_album": "album",
  "tabela_que_contem_album": "Albuns",
  "coluna_cancoes": "cancao",
  "tabela_que_contem_cancoes": "Cancoes"
}
